nonebot_plugin_b23/__init__.py
nonebot_plugin_b23/config.py
nonebot_plugin_b23-0.4.0.dist-info/LICENSE.txt
nonebot_plugin_b23-0.4.0.dist-info/METADATA
nonebot_plugin_b23-0.4.0.dist-info/WHEEL
nonebot_plugin_b23-0.4.0.dist-info/RECORD
