Metadata-Version: 2.1
Name: nonebot-plugin-b23
Version: 0.4.0
Summary: nonebot2 plugin B站热搜
Home-page: https://github.com/eya46/nonebot_plugin_b23
License: MIT
Author: eya46
Author-email: 61458340+eya46@users.noreply.github.com
Requires-Python: >=3.9,<4.0
Classifier: License :: OSI Approved :: MIT License
Classifier: Programming Language :: Python :: 3
Classifier: Programming Language :: Python :: 3.9
Classifier: Programming Language :: Python :: 3.10
Classifier: Programming Language :: Python :: 3.11
Classifier: Programming Language :: Python :: 3.12
Classifier: Programming Language :: Python :: 3.13
Requires-Dist: nonebot2[httpx] (>=2.3.0,<3.0.0)
